Metadata-Version: 2.1
Name: leg2
Version: 1.0
Summary: Learn to Pack Python Module  -->公众号：等离子工作室
Home-page: https://www.baidu.com
Author: mark-cyber-cmd
Author-email: dingyiming19991203@163.com
License: UNKNOWN
Platform: UNKNOWN
